runapi/__init__.py
runapi/auth.py
runapi/cli.py
runapi/config.py
runapi/core.py
runapi/errors.py
runapi/middleware.py
runapi/repository.py
runapi/schemas.py
runapi/service.py
runapi-0.1.3.dist-info/METADATA
runapi-0.1.3.dist-info/WHEEL
runapi-0.1.3.dist-info/entry_points.txt
runapi-0.1.3.dist-info/licenses/LICENSE
runapi-0.1.3.dist-info/RECORD
