Metadata-Version: 2.4
Name: runapi
Version: 0.1.3
Summary: A Next.js-inspired file-based routing framework built on FastAPI
Project-URL: Homepage, https://github.com/Amanbig/runapi
Project-URL: Repository, https://github.com/Amanbig/runapi
Project-URL: Documentation, https://github.com/Amanbig/runapi#readme
Project-URL: Issues, https://github.com/Amanbig/runapi/issues
Project-URL: Changelog, https://github.com/Amanbig/runapi/releases
Author-email: Amanpreet Singh <amanpreetsinghjhiwant7@gmail.com>
License: MIT License
License-File: LICENSE
Keywords: api,async,backend,fastapi,file-based-routing,framework,nextjs,web
Classifier: Development Status :: 3 - Alpha
Classifier: Environment :: Web Environment
Classifier: Framework :: FastAPI
Classifier: Intended Audience :: Developers
Classifier: License :: OSI Approved :: MIT License
Classifier: Operating System :: OS Independent
Classifier: Programming Language :: Python :: 3
Classifier: Programming Language :: Python :: 3.8
Classifier: Programming Language :: Python :: 3.9
Classifier: Programming Language :: Python :: 3.10
Classifier: Programming Language :: Python :: 3.11
Classifier: Programming Language :: Python :: 3.12
Classifier: Topic :: Internet :: WWW/HTTP :: HTTP Servers
Classifier: Topic :: Internet :: WWW/HTTP :: WSGI :: Application
Classifier: Topic :: Software Development :: Libraries :: Application Frameworks
Classifier: Topic :: Software Development :: Libraries :: Python Modules
Classifier: Typing :: Typed
Requires-Python: >=3.8
Requires-Dist: aiofiles>=23.0.0
Requires-Dist: fastapi>=0.103.0
Requires-Dist: passlib[bcrypt]>=1.7.4
Requires-Dist: psutil>=5.9.0
Requires-Dist: python-jose[cryptography]>=3.3.0
Requires-Dist: python-multipart>=0.0.6
Requires-Dist: rich>=13.0.0
Requires-Dist: typer>=0.9.0
Requires-Dist: uvicorn>=0.23.0
Provides-Extra: dev
Requires-Dist: httpx>=0.24.0; extra == 'dev'
Requires-Dist: mypy>=1.0.0; extra == 'dev'
Requires-Dist: pytest>=7.0.0; extra == 'dev'
Requires-Dist: ruff>=0.1.0; extra == 'dev'
Provides-Extra: lint
Requires-Dist: mypy>=1.0.0; extra == 'lint'
Requires-Dist: ruff>=0.1.0; extra == 'lint'
Provides-Extra: test
Requires-Dist: httpx>=0.24.0; extra == 'test'
Requires-Dist: pytest-asyncio>=0.21.0; extra == 'test'
Requires-Dist: pytest-cov>=4.0.0; extra == 'test'
Requires-Dist: pytest>=7.0.0; extra == 'test'
